aws_lambda_event_models/__init__.py
aws_lambda_event_models/aws_lambda_event_models.py
aws_lambda_event_models-0.0.1.dist-info/AUTHORS.md
aws_lambda_event_models-0.0.1.dist-info/LICENSE
aws_lambda_event_models-0.0.1.dist-info/METADATA
aws_lambda_event_models-0.0.1.dist-info/WHEEL
aws_lambda_event_models-0.0.1.dist-info/top_level.txt
aws_lambda_event_models-0.0.1.dist-info/RECORD
