Metadata-Version: 2.1
Name: aws-lambda-event-models
Version: 0.0.1
Summary: Pydantic models for AWS Events
Home-page: https://github.com/KeltonKarboviak/aws-lambda-event-models
Author: Kelton Karboviak
Author-email: kelton.karboviak@gmail.com
License: MIT license
Keywords: AWS Lambda Pydantic
Platform: UNKNOWN
Classifier: Development Status :: 2 - Pre-Alpha
Classifier: Intended Audience :: Developers
Classifier: License :: OSI Approved :: MIT License
Classifier: Natural Language :: English
Classifier: Programming Language :: Python :: 3
Classifier: Programming Language :: Python :: 3.6
Classifier: Programming Language :: Python :: 3.7
Classifier: Programming Language :: Python :: 3.8
Requires-Python: >=3.6
Requires-Dist: pydantic (>=1.2)
